{"cameraMode":{"drawMode":0,"name":"Shaded","section":"Shading Mode"},"sceneLighting":true,"audioPlay":false,"sceneViewState":{"showFog":true,"showMaterialUpdate":false,"showSkybox":true,"showFlares":true,"showImageEffects":true,"showParticleSystems":true},"in2DMode":false,"pivot":{"x":-0.1415386199951172,"y":0.8596309423446655,"z":50.06201934814453},"rotation":{"x":0.10300660133361817,"y":-0.7395442128181458,"z":0.11631400883197785,"w":0.6549325585365295},"size":2.366025447845459,"orthographic":false}